odoo8_addon_account_invoice_supplierinfo_update-8.0.1.0.0.99.dev22-py3.8-nspkg.pth
odoo_addons/account_invoice_supplierinfo_update/README.rst
odoo_addons/account_invoice_supplierinfo_update/__init__.py
odoo_addons/account_invoice_supplierinfo_update/__openerp__.py
odoo_addons/account_invoice_supplierinfo_update/demo/account_invoice.xml
odoo_addons/account_invoice_supplierinfo_update/demo/res_groups.xml
odoo_addons/account_invoice_supplierinfo_update/i18n/account_invoice_supplierinfo_update.pot
odoo_addons/account_invoice_supplierinfo_update/i18n/am.po
odoo_addons/account_invoice_supplierinfo_update/i18n/ar.po
odoo_addons/account_invoice_supplierinfo_update/i18n/bg.po
odoo_addons/account_invoice_supplierinfo_update/i18n/bs.po
odoo_addons/account_invoice_supplierinfo_update/i18n/ca.po
odoo_addons/account_invoice_supplierinfo_update/i18n/ca_ES.po
odoo_addons/account_invoice_supplierinfo_update/i18n/cs.po
odoo_addons/account_invoice_supplierinfo_update/i18n/da.po
odoo_addons/account_invoice_supplierinfo_update/i18n/de.po
odoo_addons/account_invoice_supplierinfo_update/i18n/el_GR.po
odoo_addons/account_invoice_supplierinfo_update/i18n/en_AU.po
odoo_addons/account_invoice_supplierinfo_update/i18n/en_GB.po
odoo_addons/account_invoice_supplierinfo_update/i18n/es.po
odoo_addons/account_invoice_supplierinfo_update/i18n/es_AR.po
odoo_addons/account_invoice_supplierinfo_update/i18n/es_CL.po
odoo_addons/account_invoice_supplierinfo_update/i18n/es_CO.po
odoo_addons/account_invoice_supplierinfo_update/i18n/es_CR.po
odoo_addons/account_invoice_supplierinfo_update/i18n/es_DO.po
odoo_addons/account_invoice_supplierinfo_update/i18n/es_EC.po
odoo_addons/account_invoice_supplierinfo_update/i18n/es_ES.po
odoo_addons/account_invoice_supplierinfo_update/i18n/es_MX.po
odoo_addons/account_invoice_supplierinfo_update/i18n/es_PE.po
odoo_addons/account_invoice_supplierinfo_update/i18n/es_PY.po
odoo_addons/account_invoice_supplierinfo_update/i18n/es_VE.po
odoo8_addon_account_invoice_supplierinfo_update-8.0.1.0.0.99.dev22.dist-info/METADATA
odoo8_addon_account_invoice_supplierinfo_update-8.0.1.0.0.99.dev22.dist-info/WHEEL
odoo8_addon_account_invoice_supplierinfo_update-8.0.1.0.0.99.dev22.dist-info/namespace_packages.txt
odoo8_addon_account_invoice_supplierinfo_update-8.0.1.0.0.99.dev22.dist-info/top_level.txt
odoo8_addon_account_invoice_supplierinfo_update-8.0.1.0.0.99.dev22.dist-info/RECORD
