Metadata-Version: 2.1
Name: odoo8-addon-account-invoice-supplierinfo-update
Version: 8.0.1.0.0.99.dev22
Summary: In the supplier invoice, automatically update all products whose unit price on the line is different from the supplier price
Home-page: http://akretion.com
Author: Akretion,GRAP,Odoo Community Association (OCA)
Author-email: support@odoo-community.org
License: AGPL-3
Platform: UNKNOWN
Classifier: Programming Language :: Python
Classifier: Framework :: Odoo
Classifier: Framework :: Odoo :: 8.0
Classifier: License :: OSI Approved :: GNU Affero General Public License v3
Requires-Python: ~=2.7
Requires-Dist: odoo (<9.0a,>=8.0a)
